pickledsocks/__init__.py
pickledsocks/pickledsocks.py
pickledsocks_siiverfish-0.0.1.dist-info/LICENSE
pickledsocks_siiverfish-0.0.1.dist-info/METADATA
pickledsocks_siiverfish-0.0.1.dist-info/WHEEL
pickledsocks_siiverfish-0.0.1.dist-info/top_level.txt
pickledsocks_siiverfish-0.0.1.dist-info/RECORD
